whispi/CLAUDE.md
whispi/__init__.py
whispi/cli.py
whispi/diarize_utils.py
whispi/little_helper.py
whispi/models.py
whispi/output_utils.py
whispi/transcription.py
whispi-0.1.1.dist-info/METADATA
whispi-0.1.1.dist-info/WHEEL
whispi-0.1.1.dist-info/entry_points.txt
whispi-0.1.1.dist-info/RECORD
