Metadata-Version: 2.4
Name: whispi
Version: 0.1.1
Summary: Transcribe, translate, annotate and subtitle audio and video files with OpenAI's Whisper ... fast!
Project-URL: Homepage, https://github.com/tsmdt/whispi
Project-URL: Repository, https://github.com/tsmdt/whispi
Author: NightVoyager
License: MIT
Keywords: audio,speech-to-text,subtitle,transcription,video,whisper
Classifier: Development Status :: 4 - Beta
Classifier: Intended Audience :: Developers
Classifier: License :: OSI Approved :: MIT License
Classifier: Programming Language :: Python :: 3.10
Classifier: Programming Language :: Python :: 3.11
Classifier: Programming Language :: Python :: 3.12
Classifier: Programming Language :: Python :: 3.13
Requires-Python: <3.14,>=3.10
Requires-Dist: faster-whisper==1.2.1
Requires-Dist: ffmpeg-python==0.2.0
Requires-Dist: pyannote-audio==4.0.2
Requires-Dist: rich>=13.9.4
Requires-Dist: torch==2.8.0
Requires-Dist: torchaudio==2.8.0
Requires-Dist: transformers==4.57.3
Requires-Dist: typer==0.20.0
Provides-Extra: mlx
Requires-Dist: mlx-whisper==0.4.3; extra == 'mlx'
